MANIFEST.in
README.rst
setup.py
docs/.HISTORY.rst.swp
docs/HISTORY.rst
docs/INSTALL.txt
docs/LICENSE.GPL
docs/LICENSE.txt
plone/__init__.py
plone.app.event_ploneintegration.egg-info/PKG-INFO
plone.app.event_ploneintegration.egg-info/SOURCES.txt
plone.app.event_ploneintegration.egg-info/dependency_links.txt
plone.app.event_ploneintegration.egg-info/entry_points.txt
plone.app.event_ploneintegration.egg-info/namespace_packages.txt
plone.app.event_ploneintegration.egg-info/not-zip-safe
plone.app.event_ploneintegration.egg-info/requires.txt
plone.app.event_ploneintegration.egg-info/top_level.txt
plone/app/__init__.py
plone/app/event-ploneintegration/__init__.py
plone/app/event-ploneintegration/configure.zcml
plone/app/event-ploneintegration/overrides.zcml
plone/app/event-ploneintegration/profiles/default/metadata.xml
plone/app/event-ploneintegration/profiles/prepare/catalog.xml
plone/app/event-ploneintegration/profiles/prepare/controlpanel.xml
plone/app/event-ploneintegration/profiles/prepare/metadata.xml
plone/app/event-ploneintegration/profiles/prepare/portlets.xml
plone/app/event-ploneintegration/profiles/prepare/types.xml