Metadata-Version: 1.0
Name: plone.app.event-ploneintegration
Version: 1.1
Summary: Integration of plone.app.event into pre Plone 4.3 release.
Home-page: https://github.com/collective/plone.app.event-ploneintegration
Author: Plone Foundation
Author-email: plone-developers@lists.sourceforge.net
License: GPL
Keywords: plone event
Platform: UNKNOWN
Classifier: Framework :: Plone
Classifier: Programming Language :: Python
